wsi_packer/__init__.py
wsi_packer/create_thumbnail.py
wsi_packer/packer.py
wsi_packer-0.1.0.dist-info/licenses/LICENSE
wsi_packer-0.1.0.dist-info/METADATA
wsi_packer-0.1.0.dist-info/WHEEL
wsi_packer-0.1.0.dist-info/top_level.txt
wsi_packer-0.1.0.dist-info/RECORD
